[
    {
     "help1_title": "โน๏ธ ุงููุณุงุนุฏุฉ",
     "help1_description": "**โ๏ธ ุงูุฃูุงูุฑ ุงูุฃุณุงุณูุฉ**\n%1play\n%1nowplaying\n%1leave\n\n**โ๏ธ ุฃูู ุงูุฃูุงูุฑ ? ุฌููุน ุงูุฃูุงูุฑ ูุชููุฑุฉ [ููุง](https://docs.flazebot.com/commands).**\n**โ ุฃุฑูุฏ ูุณุงุนุฏู ? ูู ุจุฒูุงุฑุฉ [ุงูุฏููู](https://docs.flazebot.com/) ูุชุฌุฏ ุชูุงุตูู ุงูุนูู !**",
     "help2_title": "โ ุฎุทุฃ",
     "help2_description": "**ูุฐุง ุงูุฃูุฑ ูู ูุชุฑุฉ ุงูุงูุชุธุงุฑ ุ ุญุงูู ูุฑุฉ ุฃุฎุฑู ุจุนุฏ** `%1`**.**",
     "help3_title": "Flaze",
     "help3_description": "ุงูุจุงุฏุฆุฉ: `%1`",
     "other1_title": "โ ุฎุทุฃ",
     "other1_description": "**ูุฐุง ุงูุฃูุฑ ูู ูุชุฑุฉ ุงูุงูุชุธุงุฑ ุ ุญุงูู ูุฑุฉ ุฃุฎุฑู ุจุนุฏ** `%1`**.**",
     "other2_title": "BENZOOgataga",
     "other2_description": "~ุฃูู~ ูู ุฃูุช ?",
     "ping1_title": "๐ถPong!",
     "ping1_description": "**๐ฅ๏ธุงูุฎุงุฏู** : %1ms\nโญ**ุงูุดุงุฑุฏ**: %2/%3, %4ms\n**๐ูุฏุฉ ุงูุชุดุบูู** : ูุนูู ููุฐ %5d %6h %7min %8s",
     "discord1_title": "ุงูุฏูุณููุฑุฏ",
     "discord1_description": "ููุง ุณูู ุชุฌุฏ ุฑุงุจุท ุงูุฏุนู ุงูููู: [discord.flazebot.com](https://discord.flazebot.com/) ุฅุฐุง ููุช ุชุญุชุงุฌ ุฅูู ูุณุงุนุฏุฉ :wink:",
     "module1_title": "ุฅููุงู",
     "module2_title": "ุชุดุบูู",
     "module3_title": "ุฅุนุฏุงุฏุช ุงูุฎุงุฏู",
     "module3_description": "**ุงูุจุงุฏุฆุฉ :** `%1`\n**ุงููุบุฉ :** ๐ต๐ธ`ุงูุนุฑุจูุฉ`",
     "module4_title": "FlazeBot's ูุนุฏ ุนูู %1",
     "module4_description": "**Documentation: https://docs.flazebot.com/**",
     "vote1_title": "๐ุงูุชุตููุช",
     "vote1_description": "**ุตูุช ูู FlazeBot**\n[Flaze's Top.gg](https://top.gg/bot/812993088749961236)\n[Flaze's Consteagle.com](https://consteagle.com/bots/812993088749961236/)\n[Flaze's Disbotlist.xyz](https://disbotlist.xyz/bot/812993088749961236#)\n[Flaze's Discordbotlist.com](https://discordbotlist.com/bots/flaze)\n\n**ุตูุช ุฅูู ุฎุงุฏู FlazeBotโข๏ธ**\n[Flaze's Top.gg](https://top.gg/servers/778284070295175188)\n[Flaze's Disbotlist.xyz](https://disbotlist.xyz/server/778284070295175188)\n[Flaze's Discordbotlist.com](https://discordbotlist.com/servers/flaze-incorporated)\n[Flaze's Disboard.org](https://disboard.org/fr/server/778284070295175188)",
     "invite1_title": "ุฅุถุงูุฉ",
     "invite1_description": "**ุชุฑูุฏูู ูู ุฎุงุฏููุ ุงุถููู :D**",
     "host1_title": "ุงููุถูู",
     "host1_description": "**ูู ุชุจุญุซ ุนู ุฎุฏูุฉ ุงุณุชุถุงูุฉ ุฌูุฏุฉ ุญููุง ูููุซููุฉ ูุฑุฎูุตุฉ ูุฐุงุช ููุช ุชุดุบูู ุฌูุฏุ ุงุชุจุน FlazeBot ูุงุฎุชุฑ ููุดุฃุฉ ูุน [RedHeberg.fr](https://redheberg.fr/)**"
    }
   ]
   
